dpn_pyutils/__init__.py
dpn_pyutils/cli.py
dpn_pyutils/common.py
dpn_pyutils/crypto.py
dpn_pyutils/exceptions.py
dpn_pyutils/file.py
dpn_pyutils/http.py
dpn_pyutils/money.py
dpn_pyutils/types.py
dpn_pyutils/logging/__init__.py
dpn_pyutils/logging/context.py
dpn_pyutils/logging/formatters.py
dpn_pyutils/logging/handlers.py
dpn_pyutils/logging/init.py
dpn_pyutils/logging/logger.py
dpn_pyutils/logging/schemas.py
dpn_pyutils/logging/state.py
dpn_pyutils/time/__init__.py
dpn_pyutils/time/periods.py
dpn_pyutils-3.12.11.dist-info/METADATA
dpn_pyutils-3.12.11.dist-info/WHEEL
dpn_pyutils-3.12.11.dist-info/licenses/LICENSE
dpn_pyutils-3.12.11.dist-info/RECORD
