Metadata-Version: 2.4
Name: dpn_pyutils
Version: 3.12.11
Summary: A collection of python utils used by the DPN
Project-URL: Homepage, https://github.com/davidpirogov/dpn_pyutils
Author-email: David Pirogov <580286+davidpirogov@users.noreply.github.com>
License: MIT License
License-File: LICENSE
Requires-Python: >=3.12
Requires-Dist: better-exceptions>=0.3.3
Requires-Dist: cachetools>=6.2.1
Requires-Dist: chardet>=5.2.0
Requires-Dist: click>=8.3.0
Requires-Dist: colorama>=0.4.6
Requires-Dist: coverage>=7.11.0
Requires-Dist: distlib>=0.4.0
Requires-Dist: filelock>=3.20.0
Requires-Dist: iniconfig>=2.1.0
Requires-Dist: lexid>=2021.1006
Requires-Dist: looseversion>=1.3.0
Requires-Dist: orjson>=3.11.3
Requires-Dist: packaging>=25.0
Requires-Dist: platformdirs>=4.5.0
Requires-Dist: pluggy>=1.6.0
Requires-Dist: pydantic>=2.12.2
Requires-Dist: pygments>=2.19.2
Requires-Dist: pyproject-api>=1.10.0
Requires-Dist: pytest>=8.4.2
Requires-Dist: pytz>=2025.2
Requires-Dist: toml>=0.10.2
Requires-Dist: tox-uv>=1.18.2
Requires-Dist: tox>=4.31.0
